module_wrapper/__init__.py
module_wrapper/__init__.pyi
module_wrapper-0.3.2.dist-info/LICENSE
module_wrapper-0.3.2.dist-info/WHEEL
module_wrapper-0.3.2.dist-info/METADATA
module_wrapper-0.3.2.dist-info/RECORD
