Metadata-Version: 2.1
Name: module-wrapper
Version: 0.3.2
Summary: Module wrapper Python library
Home-page: https://github.com/rominf/module-wrapper
License: Apache-2.0
Keywords: module,wrapper,proxy,decorator
Author: Roman Inflianskas
Author-email: infroma@gmail.com
Requires-Python: >=3.6,<3.10
Classifier: Development Status :: 7 - Inactive
Classifier: License :: OSI Approved :: Apache Software License
Classifier: Programming Language :: Python :: 3
Classifier: Programming Language :: Python :: 3.6
Classifier: Programming Language :: Python :: 3.7
Classifier: Programming Language :: Python :: 3.8
Classifier: Programming Language :: Python :: 3.9
Classifier: Topic :: Software Development :: Libraries :: Python Modules
Requires-Dist: stdlib_list (>=0.8.0,<0.9.0)
Project-URL: Repository, https://github.com/rominf/module-wrapper
